pyproject.toml
setup.cfg
setup.py
src/crosslab/soa_services/webcam/__init__.py
src/crosslab/soa_services/webcam/_media.py
src/crosslab/soa_services/webcam/media.py
src/crosslab/soa_services/webcam/messages.py
src/crosslab/soa_services/webcam/py.typed
src/crosslab/soa_services/webcam/webcam_service.py
src/crosslab_soa_service_webcam.egg-info/PKG-INFO
src/crosslab_soa_service_webcam.egg-info/SOURCES.txt
src/crosslab_soa_service_webcam.egg-info/dependency_links.txt
src/crosslab_soa_service_webcam.egg-info/requires.txt
src/crosslab_soa_service_webcam.egg-info/top_level.txt
tests/test_standard.py